TableauConMan/README
TableauConMan/__init__.py
TableauConMan/assets/__init__.py
TableauConMan/assets/asset.py
TableauConMan/assets/permission_rule_asset.py
TableauConMan/assets/project_asset.py
TableauConMan/assets_manager.py
TableauConMan/cli/__init__.py
TableauConMan/cli/__main__.py
TableauConMan/cli/cli.py
TableauConMan/cli/provisioning.py
TableauConMan/config/__init__.py
TableauConMan/config/plan_options.py
TableauConMan/config/plans.py
TableauConMan/converters/__init__.py
TableauConMan/converters/converter.py
TableauConMan/converters/permission_rule_converter.py
TableauConMan/converters/project_converter.py
TableauConMan/data_sources_manager.py
TableauConMan/example.env
TableauConMan/execute.py
TableauConMan/factories/__init__.py
TableauConMan/factories/converter_factory.py
TableauConMan/factories/manager_factory.py
TableauConMan/factories/source_factory.py
TableauConMan/groups_manager.py
TableauConMan/helpers/__init__.py
TableauConMan/helpers/utils.py
TableauConMan/managers/__init__.py
TableauConMan/managers/asset_manager.py
TableauConMan/managers/permission_rule_manager.py
TableauConMan/managers/project_manager.py
TableauConMan/plan.py
TableauConMan/projects_manager.py
TableauConMan/schemas/__init__.py
TableauConMan/schemas/graphQL_result.py
TableauConMan/schemas/plan.py
TableauConMan/schemas/spec.py
TableauConMan/server_connector.py
TableauConMan/sources/__init__.py
TableauConMan/sources/server_source.py
TableauConMan/sources/sources.py
TableauConMan/sources/specification_source.py
TableauConMan/specification.py
TableauConMan/user_manager.py
TableauConMan/workbooks_manager.py
TableauConMan/yaml_connector.py
tableauconman-0.1.18.dist-info/AUTHORS.rst
tableauconman-0.1.18.dist-info/LICENSE
tableauconman-0.1.18.dist-info/METADATA
tableauconman-0.1.18.dist-info/WHEEL
tableauconman-0.1.18.dist-info/entry_points.txt
tableauconman-0.1.18.dist-info/RECORD
