Metadata-Version: 2.1
Name: TableauConMan
Version: 0.1.18
Summary: 
Home-page: https://gitlab.com/gitlab-data/TableauConMan
Keywords: TableauConMan
Author: GitLab data team
Requires-Python: >=3.8.0,<4.0.0
Classifier: Development Status :: 2 - Pre-Alpha
Classifier: Intended Audience :: Developers
Classifier: License :: OSI Approved :: MIT License
Classifier: Natural Language :: English
Classifier: Programming Language :: Python :: 3
Classifier: Programming Language :: Python :: 3.8
Classifier: Programming Language :: Python :: 3.9
Classifier: Programming Language :: Python :: 3.10
Classifier: Programming Language :: Python :: 3.11
Classifier: Programming Language :: Python :: 3.12
Classifier: Programming Language :: Python :: 3.6
Classifier: Programming Language :: Python :: 3.7
Requires-Dist: cerberus (>=1.3.5,<2.0.0)
Requires-Dist: click (==8.1.7)
Requires-Dist: coverage (>=7.3.2,<8.0.0)
Requires-Dist: jinja2 (>=3.1.2,<4.0.0)
Requires-Dist: loguru (==0.7.2)
Requires-Dist: mypy (>=1.6.1,<2.0.0)
Requires-Dist: pylint (>=3.0.2,<4.0.0)
Requires-Dist: pytest (>=7.4.3,<8.0.0)
Requires-Dist: python-dotenv (==1.0.0)
Requires-Dist: pyyaml (==6.0.0)
Requires-Dist: requests (>=2.31.0,<3.0.0)
Requires-Dist: selenium (>=4.14.0,<5.0.0)
Requires-Dist: tableauserverclient (==0.30)
Requires-Dist: treelib (>=1.6.4,<2.0.0)
Project-URL: Repository, https://gitlab.com/gitlab-data/TableauConMan
